{
  "type": "File",
  "start": 0,
  "end": 485,
  "loc": {
    "start": {
      "line": 1,
      "column": 0
    },
    "end": {
      "line": 25,
      "column": 0
    }
  },
  "program": {
    "type": "Program",
    "start": 0,
    "end": 485,
    "loc": {
      "start": {
        "line": 1,
        "column": 0
      },
      "end": {
        "line": 25,
        "column": 0
      }
    },
    "sourceType": "module",
    "body": [
      {
        "type": "ExportDefaultDeclaration",
        "start": 71,
        "end": 484,
        "loc": {
          "start": {
            "line": 5,
            "column": 0
          },
          "end": {
            "line": 24,
            "column": 1
          }
        },
        "declaration": {
          "type": "ClassDeclaration",
          "start": 86,
          "end": 484,
          "loc": {
            "start": {
              "line": 5,
              "column": 15
            },
            "end": {
              "line": 24,
              "column": 1
            }
          },
          "id": {
            "type": "Identifier",
            "start": 92,
            "end": 107,
            "loc": {
              "start": {
                "line": 5,
                "column": 21
              },
              "end": {
                "line": 5,
                "column": 36
              },
              "identifierName": "ExtendableError"
            },
            "name": "ExtendableError",
            "leadingComments": null
          },
          "superClass": {
            "type": "Identifier",
            "start": 116,
            "end": 121,
            "loc": {
              "start": {
                "line": 5,
                "column": 45
              },
              "end": {
                "line": 5,
                "column": 50
              },
              "identifierName": "Error"
            },
            "name": "Error"
          },
          "body": {
            "type": "ClassBody",
            "start": 122,
            "end": 484,
            "loc": {
              "start": {
                "line": 5,
                "column": 51
              },
              "end": {
                "line": 24,
                "column": 1
              }
            },
            "body": [
              {
                "type": "ClassMethod",
                "start": 151,
                "end": 482,
                "loc": {
                  "start": {
                    "line": 9,
                    "column": 2
                  },
                  "end": {
                    "line": 23,
                    "column": 3
                  }
                },
                "static": false,
                "computed": false,
                "key": {
                  "type": "Identifier",
                  "start": 151,
                  "end": 162,
                  "loc": {
                    "start": {
                      "line": 9,
                      "column": 2
                    },
                    "end": {
                      "line": 9,
                      "column": 13
                    },
                    "identifierName": "constructor"
                  },
                  "name": "constructor",
                  "leadingComments": null
                },
                "kind": "constructor",
                "id": null,
                "generator": false,
                "expression": false,
                "async": false,
                "params": [
                  {
                    "type": "Identifier",
                    "start": 163,
                    "end": 170,
                    "loc": {
                      "start": {
                        "line": 9,
                        "column": 14
                      },
                      "end": {
                        "line": 9,
                        "column": 21
                      },
                      "identifierName": "message"
                    },
                    "name": "message"
                  }
                ],
                "body": {
                  "type": "BlockStatement",
                  "start": 172,
                  "end": 482,
                  "loc": {
                    "start": {
                      "line": 9,
                      "column": 23
                    },
                    "end": {
                      "line": 23,
                      "column": 3
                    }
                  },
                  "body": [
                    {
                      "type": "ExpressionStatement",
                      "start": 178,
                      "end": 193,
                      "loc": {
                        "start": {
                          "line": 10,
                          "column": 4
                        },
                        "end": {
                          "line": 10,
                          "column": 19
                        }
                      },
                      "expression": {
                        "type": "CallExpression",
                        "start": 178,
                        "end": 192,
                        "loc": {
                          "start": {
                            "line": 10,
                            "column": 4
                          },
                          "end": {
                            "line": 10,
                            "column": 18
                          }
                        },
                        "callee": {
                          "type": "Super",
                          "start": 178,
                          "end": 183,
                          "loc": {
                            "start": {
                              "line": 10,
                              "column": 4
                            },
                            "end": {
                              "line": 10,
                              "column": 9
                            }
                          }
                        },
                        "arguments": [
                          {
                            "type": "Identifier",
                            "start": 184,
                            "end": 191,
                            "loc": {
                              "start": {
                                "line": 10,
                                "column": 10
                              },
                              "end": {
                                "line": 10,
                                "column": 17
                              },
                              "identifierName": "message"
                            },
                            "name": "message"
                          }
                        ]
                      },
                      "trailingComments": [
                        {
                          "type": "CommentBlock",
                          "value": "*\n     * @ignore\n     ",
                          "start": 198,
                          "end": 224,
                          "loc": {
                            "start": {
                              "line": 11,
                              "column": 4
                            },
                            "end": {
                              "line": 13,
                              "column": 7
                            }
                          }
                        }
                      ]
                    },
                    {
                      "type": "ExpressionStatement",
                      "start": 229,
                      "end": 263,
                      "loc": {
                        "start": {
                          "line": 14,
                          "column": 4
                        },
                        "end": {
                          "line": 14,
                          "column": 38
                        }
                      },
                      "expression": {
                        "type": "AssignmentExpression",
                        "start": 229,
                        "end": 262,
                        "loc": {
                          "start": {
                            "line": 14,
                            "column": 4
                          },
                          "end": {
                            "line": 14,
                            "column": 37
                          }
                        },
                        "operator": "=",
                        "left": {
                          "type": "MemberExpression",
                          "start": 229,
                          "end": 238,
                          "loc": {
                            "start": {
                              "line": 14,
                              "column": 4
                            },
                            "end": {
                              "line": 14,
                              "column": 13
                            }
                          },
                          "object": {
                            "type": "ThisExpression",
                            "start": 229,
                            "end": 233,
                            "loc": {
                              "start": {
                                "line": 14,
                                "column": 4
                              },
                              "end": {
                                "line": 14,
                                "column": 8
                              }
                            },
                            "leadingComments": null
                          },
                          "property": {
                            "type": "Identifier",
                            "start": 234,
                            "end": 238,
                            "loc": {
                              "start": {
                                "line": 14,
                                "column": 9
                              },
                              "end": {
                                "line": 14,
                                "column": 13
                              },
                              "identifierName": "name"
                            },
                            "name": "name"
                          },
                          "computed": false,
                          "leadingComments": null
                        },
                        "right": {
                          "type": "MemberExpression",
                          "start": 241,
                          "end": 262,
                          "loc": {
                            "start": {
                              "line": 14,
                              "column": 16
                            },
                            "end": {
                              "line": 14,
                              "column": 37
                            }
                          },
                          "object": {
                            "type": "MemberExpression",
                            "start": 241,
                            "end": 257,
                            "loc": {
                              "start": {
                                "line": 14,
                                "column": 16
                              },
                              "end": {
                                "line": 14,
                                "column": 32
                              }
                            },
                            "object": {
                              "type": "ThisExpression",
                              "start": 241,
                              "end": 245,
                              "loc": {
                                "start": {
                                  "line": 14,
                                  "column": 16
                                },
                                "end": {
                                  "line": 14,
                                  "column": 20
                                }
                              }
                            },
                            "property": {
                              "type": "Identifier",
                              "start": 246,
                              "end": 257,
                              "loc": {
                                "start": {
                                  "line": 14,
                                  "column": 21
                                },
                                "end": {
                                  "line": 14,
                                  "column": 32
                                },
                                "identifierName": "constructor"
                              },
                              "name": "constructor"
                            },
                            "computed": false
                          },
                          "property": {
                            "type": "Identifier",
                            "start": 258,
                            "end": 262,
                            "loc": {
                              "start": {
                                "line": 14,
                                "column": 33
                              },
                              "end": {
                                "line": 14,
                                "column": 37
                              },
                              "identifierName": "name"
                            },
                            "name": "name"
                          },
                          "computed": false
                        },
                        "leadingComments": null
                      },
                      "leadingComments": [
                        {
                          "type": "CommentBlock",
                          "value": "*\n     * @ignore\n     ",
                          "start": 198,
                          "end": 224,
                          "loc": {
                            "start": {
                              "line": 11,
                              "column": 4
                            },
                            "end": {
                              "line": 13,
                              "column": 7
                            }
                          }
                        }
                      ]
                    },
                    {
                      "type": "IfStatement",
                      "start": 268,
                      "end": 478,
                      "loc": {
                        "start": {
                          "line": 15,
                          "column": 4
                        },
                        "end": {
                          "line": 22,
                          "column": 5
                        }
                      },
                      "test": {
                        "type": "BinaryExpression",
                        "start": 272,
                        "end": 317,
                        "loc": {
                          "start": {
                            "line": 15,
                            "column": 8
                          },
                          "end": {
                            "line": 15,
                            "column": 53
                          }
                        },
                        "left": {
                          "type": "UnaryExpression",
                          "start": 272,
                          "end": 302,
                          "loc": {
                            "start": {
                              "line": 15,
                              "column": 8
                            },
                            "end": {
                              "line": 15,
                              "column": 38
                            }
                          },
                          "operator": "typeof",
                          "prefix": true,
                          "argument": {
                            "type": "MemberExpression",
                            "start": 279,
                            "end": 302,
                            "loc": {
                              "start": {
                                "line": 15,
                                "column": 15
                              },
                              "end": {
                                "line": 15,
                                "column": 38
                              }
                            },
                            "object": {
                              "type": "Identifier",
                              "start": 279,
                              "end": 284,
                              "loc": {
                                "start": {
                                  "line": 15,
                                  "column": 15
                                },
                                "end": {
                                  "line": 15,
                                  "column": 20
                                },
                                "identifierName": "Error"
                              },
                              "name": "Error"
                            },
                            "property": {
                              "type": "Identifier",
                              "start": 285,
                              "end": 302,
                              "loc": {
                                "start": {
                                  "line": 15,
                                  "column": 21
                                },
                                "end": {
                                  "line": 15,
                                  "column": 38
                                },
                                "identifierName": "captureStackTrace"
                              },
                              "name": "captureStackTrace"
                            },
                            "computed": false
                          },
                          "extra": {
                            "parenthesizedArgument": false
                          }
                        },
                        "operator": "===",
                        "right": {
                          "type": "StringLiteral",
                          "start": 307,
                          "end": 317,
                          "loc": {
                            "start": {
                              "line": 15,
                              "column": 43
                            },
                            "end": {
                              "line": 15,
                              "column": 53
                            }
                          },
                          "extra": {
                            "rawValue": "function",
                            "raw": "'function'"
                          },
                          "value": "function"
                        }
                      },
                      "consequent": {
                        "type": "BlockStatement",
                        "start": 319,
                        "end": 381,
                        "loc": {
                          "start": {
                            "line": 15,
                            "column": 55
                          },
                          "end": {
                            "line": 17,
                            "column": 5
                          }
                        },
                        "body": [
                          {
                            "type": "ExpressionStatement",
                            "start": 327,
                            "end": 375,
                            "loc": {
                              "start": {
                                "line": 16,
                                "column": 6
                              },
                              "end": {
                                "line": 16,
                                "column": 54
                              }
                            },
                            "expression": {
                              "type": "CallExpression",
                              "start": 327,
                              "end": 374,
                              "loc": {
                                "start": {
                                  "line": 16,
                                  "column": 6
                                },
                                "end": {
                                  "line": 16,
                                  "column": 53
                                }
                              },
                              "callee": {
                                "type": "MemberExpression",
                                "start": 327,
                                "end": 350,
                                "loc": {
                                  "start": {
                                    "line": 16,
                                    "column": 6
                                  },
                                  "end": {
                                    "line": 16,
                                    "column": 29
                                  }
                                },
                                "object": {
                                  "type": "Identifier",
                                  "start": 327,
                                  "end": 332,
                                  "loc": {
                                    "start": {
                                      "line": 16,
                                      "column": 6
                                    },
                                    "end": {
                                      "line": 16,
                                      "column": 11
                                    },
                                    "identifierName": "Error"
                                  },
                                  "name": "Error"
                                },
                                "property": {
                                  "type": "Identifier",
                                  "start": 333,
                                  "end": 350,
                                  "loc": {
                                    "start": {
                                      "line": 16,
                                      "column": 12
                                    },
                                    "end": {
                                      "line": 16,
                                      "column": 29
                                    },
                                    "identifierName": "captureStackTrace"
                                  },
                                  "name": "captureStackTrace"
                                },
                                "computed": false
                              },
                              "arguments": [
                                {
                                  "type": "ThisExpression",
                                  "start": 351,
                                  "end": 355,
                                  "loc": {
                                    "start": {
                                      "line": 16,
                                      "column": 30
                                    },
                                    "end": {
                                      "line": 16,
                                      "column": 34
                                    }
                                  }
                                },
                                {
                                  "type": "MemberExpression",
                                  "start": 357,
                                  "end": 373,
                                  "loc": {
                                    "start": {
                                      "line": 16,
                                      "column": 36
                                    },
                                    "end": {
                                      "line": 16,
                                      "column": 52
                                    }
                                  },
                                  "object": {
                                    "type": "ThisExpression",
                                    "start": 357,
                                    "end": 361,
                                    "loc": {
                                      "start": {
                                        "line": 16,
                                        "column": 36
                                      },
                                      "end": {
                                        "line": 16,
                                        "column": 40
                                      }
                                    }
                                  },
                                  "property": {
                                    "type": "Identifier",
                                    "start": 362,
                                    "end": 373,
                                    "loc": {
                                      "start": {
                                        "line": 16,
                                        "column": 41
                                      },
                                      "end": {
                                        "line": 16,
                                        "column": 52
                                      },
                                      "identifierName": "constructor"
                                    },
                                    "name": "constructor"
                                  },
                                  "computed": false
                                }
                              ]
                            }
                          }
                        ],
                        "directives": []
                      },
                      "alternate": {
                        "type": "BlockStatement",
                        "start": 387,
                        "end": 478,
                        "loc": {
                          "start": {
                            "line": 17,
                            "column": 11
                          },
                          "end": {
                            "line": 22,
                            "column": 5
                          }
                        },
                        "body": [
                          {
                            "type": "ExpressionStatement",
                            "start": 432,
                            "end": 472,
                            "loc": {
                              "start": {
                                "line": 21,
                                "column": 6
                              },
                              "end": {
                                "line": 21,
                                "column": 46
                              }
                            },
                            "expression": {
                              "type": "AssignmentExpression",
                              "start": 432,
                              "end": 471,
                              "loc": {
                                "start": {
                                  "line": 21,
                                  "column": 6
                                },
                                "end": {
                                  "line": 21,
                                  "column": 45
                                }
                              },
                              "operator": "=",
                              "left": {
                                "type": "MemberExpression",
                                "start": 432,
                                "end": 442,
                                "loc": {
                                  "start": {
                                    "line": 21,
                                    "column": 6
                                  },
                                  "end": {
                                    "line": 21,
                                    "column": 16
                                  }
                                },
                                "object": {
                                  "type": "ThisExpression",
                                  "start": 432,
                                  "end": 436,
                                  "loc": {
                                    "start": {
                                      "line": 21,
                                      "column": 6
                                    },
                                    "end": {
                                      "line": 21,
                                      "column": 10
                                    }
                                  },
                                  "leadingComments": null
                                },
                                "property": {
                                  "type": "Identifier",
                                  "start": 437,
                                  "end": 442,
                                  "loc": {
                                    "start": {
                                      "line": 21,
                                      "column": 11
                                    },
                                    "end": {
                                      "line": 21,
                                      "column": 16
                                    },
                                    "identifierName": "stack"
                                  },
                                  "name": "stack"
                                },
                                "computed": false,
                                "leadingComments": null
                              },
                              "right": {
                                "type": "MemberExpression",
                                "start": 445,
                                "end": 471,
                                "loc": {
                                  "start": {
                                    "line": 21,
                                    "column": 19
                                  },
                                  "end": {
                                    "line": 21,
                                    "column": 45
                                  }
                                },
                                "object": {
                                  "type": "NewExpression",
                                  "start": 446,
                                  "end": 464,
                                  "loc": {
                                    "start": {
                                      "line": 21,
                                      "column": 20
                                    },
                                    "end": {
                                      "line": 21,
                                      "column": 38
                                    }
                                  },
                                  "callee": {
                                    "type": "Identifier",
                                    "start": 450,
                                    "end": 455,
                                    "loc": {
                                      "start": {
                                        "line": 21,
                                        "column": 24
                                      },
                                      "end": {
                                        "line": 21,
                                        "column": 29
                                      },
                                      "identifierName": "Error"
                                    },
                                    "name": "Error"
                                  },
                                  "arguments": [
                                    {
                                      "type": "Identifier",
                                      "start": 456,
                                      "end": 463,
                                      "loc": {
                                        "start": {
                                          "line": 21,
                                          "column": 30
                                        },
                                        "end": {
                                          "line": 21,
                                          "column": 37
                                        },
                                        "identifierName": "message"
                                      },
                                      "name": "message"
                                    }
                                  ],
                                  "extra": {
                                    "parenthesized": true,
                                    "parenStart": 445
                                  }
                                },
                                "property": {
                                  "type": "Identifier",
                                  "start": 466,
                                  "end": 471,
                                  "loc": {
                                    "start": {
                                      "line": 21,
                                      "column": 40
                                    },
                                    "end": {
                                      "line": 21,
                                      "column": 45
                                    },
                                    "identifierName": "stack"
                                  },
                                  "name": "stack"
                                },
                                "computed": false
                              },
                              "leadingComments": null
                            },
                            "leadingComments": [
                              {
                                "type": "CommentBlock",
                                "value": "*\n       * @ignore\n       ",
                                "start": 395,
                                "end": 425,
                                "loc": {
                                  "start": {
                                    "line": 18,
                                    "column": 6
                                  },
                                  "end": {
                                    "line": 20,
                                    "column": 9
                                  }
                                }
                              }
                            ]
                          }
                        ],
                        "directives": []
                      }
                    }
                  ],
                  "directives": []
                },
                "leadingComments": [
                  {
                    "type": "CommentBlock",
                    "value": "*\n   * @ignore\n   ",
                    "start": 126,
                    "end": 148,
                    "loc": {
                      "start": {
                        "line": 6,
                        "column": 2
                      },
                      "end": {
                        "line": 8,
                        "column": 5
                      }
                    }
                  }
                ]
              }
            ]
          },
          "leadingComments": [
            {
              "type": "CommentBlock",
              "value": "*\n * @ignore\n * @see https://stackoverflow.com/a/32749533/399105\n ",
              "start": 0,
              "end": 70,
              "loc": {
                "start": {
                  "line": 1,
                  "column": 0
                },
                "end": {
                  "line": 4,
                  "column": 3
                }
              }
            }
          ],
          "trailingComments": []
        },
        "leadingComments": [
          {
            "type": "CommentBlock",
            "value": "*\n * @ignore\n * @see https://stackoverflow.com/a/32749533/399105\n ",
            "start": 0,
            "end": 70,
            "loc": {
              "start": {
                "line": 1,
                "column": 0
              },
              "end": {
                "line": 4,
                "column": 3
              }
            }
          }
        ]
      }
    ],
    "directives": []
  },
  "comments": [
    {
      "type": "CommentBlock",
      "value": "*\n * @ignore\n * @see https://stackoverflow.com/a/32749533/399105\n ",
      "start": 0,
      "end": 70,
      "loc": {
        "start": {
          "line": 1,
          "column": 0
        },
        "end": {
          "line": 4,
          "column": 3
        }
      }
    },
    {
      "type": "CommentBlock",
      "value": "*\n   * @ignore\n   ",
      "start": 126,
      "end": 148,
      "loc": {
        "start": {
          "line": 6,
          "column": 2
        },
        "end": {
          "line": 8,
          "column": 5
        }
      }
    },
    {
      "type": "CommentBlock",
      "value": "*\n     * @ignore\n     ",
      "start": 198,
      "end": 224,
      "loc": {
        "start": {
          "line": 11,
          "column": 4
        },
        "end": {
          "line": 13,
          "column": 7
        }
      }
    },
    {
      "type": "CommentBlock",
      "value": "*\n       * @ignore\n       ",
      "start": 395,
      "end": 425,
      "loc": {
        "start": {
          "line": 18,
          "column": 6
        },
        "end": {
          "line": 20,
          "column": 9
        }
      }
    }
  ],
  "tokens": [
    {
      "type": "CommentBlock",
      "value": "*\n * @ignore\n * @see https://stackoverflow.com/a/32749533/399105\n ",
      "start": 0,
      "end": 70,
      "loc": {
        "start": {
          "line": 1,
          "column": 0
        },
        "end": {
          "line": 4,
          "column": 3
        }
      }
    },
    {
      "type": {
        "label": "export",
        "keyword": "export",
        "beforeExpr": false,
        "startsExpr": false,
        "rightAssociative": false,
        "isLoop": false,
        "isAssign": false,
        "prefix": false,
        "postfix": false,
        "binop": null,
        "updateContext": null
      },
      "value": "export",
      "start": 71,
      "end": 77,
      "loc": {
        "start": {
          "line": 5,
          "column": 0
        },
        "end": {
          "line": 5,
          "column": 6
        }
      }
    },
    {
      "type": {
        "label": "default",
        "keyword": "default",
        "beforeExpr": true,
        "startsExpr": false,
        "rightAssociative": false,
        "isLoop": false,
        "isAssign": false,
        "prefix": false,
        "postfix": false,
        "binop": null,
        "updateContext": null
      },
      "value": "default",
      "start": 78,
      "end": 85,
      "loc": {
        "start": {
          "line": 5,
          "column": 7
        },
        "end": {
          "line": 5,
          "column": 14
        }
      }
    },
    {
      "type": {
        "label": "class",
        "keyword": "class",
        "beforeExpr": false,
        "startsExpr": false,
        "rightAssociative": false,
        "isLoop": false,
        "isAssign": false,
        "prefix": false,
        "postfix": false,
        "binop": null,
        "updateContext": null
      },
      "value": "class",
      "start": 86,
      "end": 91,
      "loc": {
        "start": {
          "line": 5,
          "column": 15
        },
        "end": {
          "line": 5,
          "column": 20
        }
      }
    },
    {
      "type": {
        "label": "name",
        "beforeExpr": false,
        "startsExpr": true,
        "rightAssociative": false,
        "isLoop": false,
        "isAssign": false,
        "prefix": false,
        "postfix": false,
        "binop": null
      },
      "value": "ExtendableError",
      "start": 92,
      "end": 107,
      "loc": {
        "start": {
          "line": 5,
          "column": 21
        },
        "end": {
          "line": 5,
          "column": 36
        }
      }
    },
    {
      "type": {
        "label": "extends",
        "keyword": "extends",
        "beforeExpr": true,
        "startsExpr": false,
        "rightAssociative": false,
        "isLoop": false,
        "isAssign": false,
        "prefix": false,
        "postfix": false,
        "binop": null,
        "updateContext": null
      },
      "value": "extends",
      "start": 108,
      "end": 115,
      "loc": {
        "start": {
          "line": 5,
          "column": 37
        },
        "end": {
          "line": 5,
          "column": 44
        }
      }
    },
    {
      "type": {
        "label": "name",
        "beforeExpr": false,
        "startsExpr": true,
        "rightAssociative": false,
        "isLoop": false,
        "isAssign": false,
        "prefix": false,
        "postfix": false,
        "binop": null
      },
      "value": "Error",
      "start": 116,
      "end": 121,
      "loc": {
        "start": {
          "line": 5,
          "column": 45
        },
        "end": {
          "line": 5,
          "column": 50
        }
      }
    },
    {
      "type": {
        "label": "{",
        "beforeExpr": true,
        "startsExpr": true,
        "rightAssociative": false,
        "isLoop": false,
        "isAssign": false,
        "prefix": false,
        "postfix": false,
        "binop": null
      },
      "start": 122,
      "end": 123,
      "loc": {
        "start": {
          "line": 5,
          "column": 51
        },
        "end": {
          "line": 5,
          "column": 52
        }
      }
    },
    {
      "type": "CommentBlock",
      "value": "*\n   * @ignore\n   ",
      "start": 126,
      "end": 148,
      "loc": {
        "start": {
          "line": 6,
          "column": 2
        },
        "end": {
          "line": 8,
          "column": 5
        }
      }
    },
    {
      "type": {
        "label": "name",
        "beforeExpr": false,
        "startsExpr": true,
        "rightAssociative": false,
        "isLoop": false,
        "isAssign": false,
        "prefix": false,
        "postfix": false,
        "binop": null
      },
      "value": "constructor",
      "start": 151,
      "end": 162,
      "loc": {
        "start": {
          "line": 9,
          "column": 2
        },
        "end": {
          "line": 9,
          "column": 13
        }
      }
    },
    {
      "type": {
        "label": "(",
        "beforeExpr": true,
        "startsExpr": true,
        "rightAssociative": false,
        "isLoop": false,
        "isAssign": false,
        "prefix": false,
        "postfix": false,
        "binop": null
      },
      "start": 162,
      "end": 163,
      "loc": {
        "start": {
          "line": 9,
          "column": 13
        },
        "end": {
          "line": 9,
          "column": 14
        }
      }
    },
    {
      "type": {
        "label": "name",
        "beforeExpr": false,
        "startsExpr": true,
        "rightAssociative": false,
        "isLoop": false,
        "isAssign": false,
        "prefix": false,
        "postfix": false,
        "binop": null
      },
      "value": "message",
      "start": 163,
      "end": 170,
      "loc": {
        "start": {
          "line": 9,
          "column": 14
        },
        "end": {
          "line": 9,
          "column": 21
        }
      }
    },
    {
      "type": {
        "label": ")",
        "beforeExpr": false,
        "startsExpr": false,
        "rightAssociative": false,
        "isLoop": false,
        "isAssign": false,
        "prefix": false,
        "postfix": false,
        "binop": null
      },
      "start": 170,
      "end": 171,
      "loc": {
        "start": {
          "line": 9,
          "column": 21
        },
        "end": {
          "line": 9,
          "column": 22
        }
      }
    },
    {
      "type": {
        "label": "{",
        "beforeExpr": true,
        "startsExpr": true,
        "rightAssociative": false,
        "isLoop": false,
        "isAssign": false,
        "prefix": false,
        "postfix": false,
        "binop": null
      },
      "start": 172,
      "end": 173,
      "loc": {
        "start": {
          "line": 9,
          "column": 23
        },
        "end": {
          "line": 9,
          "column": 24
        }
      }
    },
    {
      "type": {
        "label": "super",
        "keyword": "super",
        "beforeExpr": false,
        "startsExpr": true,
        "rightAssociative": false,
        "isLoop": false,
        "isAssign": false,
        "prefix": false,
        "postfix": false,
        "binop": null,
        "updateContext": null
      },
      "value": "super",
      "start": 178,
      "end": 183,
      "loc": {
        "start": {
          "line": 10,
          "column": 4
        },
        "end": {
          "line": 10,
          "column": 9
        }
      }
    },
    {
      "type": {
        "label": "(",
        "beforeExpr": true,
        "startsExpr": true,
        "rightAssociative": false,
        "isLoop": false,
        "isAssign": false,
        "prefix": false,
        "postfix": false,
        "binop": null
      },
      "start": 183,
      "end": 184,
      "loc": {
        "start": {
          "line": 10,
          "column": 9
        },
        "end": {
          "line": 10,
          "column": 10
        }
      }
    },
    {
      "type": {
        "label": "name",
        "beforeExpr": false,
        "startsExpr": true,
        "rightAssociative": false,
        "isLoop": false,
        "isAssign": false,
        "prefix": false,
        "postfix": false,
        "binop": null
      },
      "value": "message",
      "start": 184,
      "end": 191,
      "loc": {
        "start": {
          "line": 10,
          "column": 10
        },
        "end": {
          "line": 10,
          "column": 17
        }
      }
    },
    {
      "type": {
        "label": ")",
        "beforeExpr": false,
        "startsExpr": false,
        "rightAssociative": false,
        "isLoop": false,
        "isAssign": false,
        "prefix": false,
        "postfix": false,
        "binop": null
      },
      "start": 191,
      "end": 192,
      "loc": {
        "start": {
          "line": 10,
          "column": 17
        },
        "end": {
          "line": 10,
          "column": 18
        }
      }
    },
    {
      "type": {
        "label": ";",
        "beforeExpr": true,
        "startsExpr": false,
        "rightAssociative": false,
        "isLoop": false,
        "isAssign": false,
        "prefix": false,
        "postfix": false,
        "binop": null,
        "updateContext": null
      },
      "start": 192,
      "end": 193,
      "loc": {
        "start": {
          "line": 10,
          "column": 18
        },
        "end": {
          "line": 10,
          "column": 19
        }
      }
    },
    {
      "type": "CommentBlock",
      "value": "*\n     * @ignore\n     ",
      "start": 198,
      "end": 224,
      "loc": {
        "start": {
          "line": 11,
          "column": 4
        },
        "end": {
          "line": 13,
          "column": 7
        }
      }
    },
    {
      "type": {
        "label": "this",
        "keyword": "this",
        "beforeExpr": false,
        "startsExpr": true,
        "rightAssociative": false,
        "isLoop": false,
        "isAssign": false,
        "prefix": false,
        "postfix": false,
        "binop": null,
        "updateContext": null
      },
      "value": "this",
      "start": 229,
      "end": 233,
      "loc": {
        "start": {
          "line": 14,
          "column": 4
        },
        "end": {
          "line": 14,
          "column": 8
        }
      }
    },
    {
      "type": {
        "label": ".",
        "beforeExpr": false,
        "startsExpr": false,
        "rightAssociative": false,
        "isLoop": false,
        "isAssign": false,
        "prefix": false,
        "postfix": false,
        "binop": null,
        "updateContext": null
      },
      "start": 233,
      "end": 234,
      "loc": {
        "start": {
          "line": 14,
          "column": 8
        },
        "end": {
          "line": 14,
          "column": 9
        }
      }
    },
    {
      "type": {
        "label": "name",
        "beforeExpr": false,
        "startsExpr": true,
        "rightAssociative": false,
        "isLoop": false,
        "isAssign": false,
        "prefix": false,
        "postfix": false,
        "binop": null
      },
      "value": "name",
      "start": 234,
      "end": 238,
      "loc": {
        "start": {
          "line": 14,
          "column": 9
        },
        "end": {
          "line": 14,
          "column": 13
        }
      }
    },
    {
      "type": {
        "label": "=",
        "beforeExpr": true,
        "startsExpr": false,
        "rightAssociative": false,
        "isLoop": false,
        "isAssign": true,
        "prefix": false,
        "postfix": false,
        "binop": null,
        "updateContext": null
      },
      "value": "=",
      "start": 239,
      "end": 240,
      "loc": {
        "start": {
          "line": 14,
          "column": 14
        },
        "end": {
          "line": 14,
          "column": 15
        }
      }
    },
    {
      "type": {
        "label": "this",
        "keyword": "this",
        "beforeExpr": false,
        "startsExpr": true,
        "rightAssociative": false,
        "isLoop": false,
        "isAssign": false,
        "prefix": false,
        "postfix": false,
        "binop": null,
        "updateContext": null
      },
      "value": "this",
      "start": 241,
      "end": 245,
      "loc": {
        "start": {
          "line": 14,
          "column": 16
        },
        "end": {
          "line": 14,
          "column": 20
        }
      }
    },
    {
      "type": {
        "label": ".",
        "beforeExpr": false,
        "startsExpr": false,
        "rightAssociative": false,
        "isLoop": false,
        "isAssign": false,
        "prefix": false,
        "postfix": false,
        "binop": null,
        "updateContext": null
      },
      "start": 245,
      "end": 246,
      "loc": {
        "start": {
          "line": 14,
          "column": 20
        },
        "end": {
          "line": 14,
          "column": 21
        }
      }
    },
    {
      "type": {
        "label": "name",
        "beforeExpr": false,
        "startsExpr": true,
        "rightAssociative": false,
        "isLoop": false,
        "isAssign": false,
        "prefix": false,
        "postfix": false,
        "binop": null
      },
      "value": "constructor",
      "start": 246,
      "end": 257,
      "loc": {
        "start": {
          "line": 14,
          "column": 21
        },
        "end": {
          "line": 14,
          "column": 32
        }
      }
    },
    {
      "type": {
        "label": ".",
        "beforeExpr": false,
        "startsExpr": false,
        "rightAssociative": false,
        "isLoop": false,
        "isAssign": false,
        "prefix": false,
        "postfix": false,
        "binop": null,
        "updateContext": null
      },
      "start": 257,
      "end": 258,
      "loc": {
        "start": {
          "line": 14,
          "column": 32
        },
        "end": {
          "line": 14,
          "column": 33
        }
      }
    },
    {
      "type": {
        "label": "name",
        "beforeExpr": false,
        "startsExpr": true,
        "rightAssociative": false,
        "isLoop": false,
        "isAssign": false,
        "prefix": false,
        "postfix": false,
        "binop": null
      },
      "value": "name",
      "start": 258,
      "end": 262,
      "loc": {
        "start": {
          "line": 14,
          "column": 33
        },
        "end": {
          "line": 14,
          "column": 37
        }
      }
    },
    {
      "type": {
        "label": ";",
        "beforeExpr": true,
        "startsExpr": false,
        "rightAssociative": false,
        "isLoop": false,
        "isAssign": false,
        "prefix": false,
        "postfix": false,
        "binop": null,
        "updateContext": null
      },
      "start": 262,
      "end": 263,
      "loc": {
        "start": {
          "line": 14,
          "column": 37
        },
        "end": {
          "line": 14,
          "column": 38
        }
      }
    },
    {
      "type": {
        "label": "if",
        "keyword": "if",
        "beforeExpr": false,
        "startsExpr": false,
        "rightAssociative": false,
        "isLoop": false,
        "isAssign": false,
        "prefix": false,
        "postfix": false,
        "binop": null,
        "updateContext": null
      },
      "value": "if",
      "start": 268,
      "end": 270,
      "loc": {
        "start": {
          "line": 15,
          "column": 4
        },
        "end": {
          "line": 15,
          "column": 6
        }
      }
    },
    {
      "type": {
        "label": "(",
        "beforeExpr": true,
        "startsExpr": true,
        "rightAssociative": false,
        "isLoop": false,
        "isAssign": false,
        "prefix": false,
        "postfix": false,
        "binop": null
      },
      "start": 271,
      "end": 272,
      "loc": {
        "start": {
          "line": 15,
          "column": 7
        },
        "end": {
          "line": 15,
          "column": 8
        }
      }
    },
    {
      "type": {
        "label": "typeof",
        "keyword": "typeof",
        "beforeExpr": true,
        "startsExpr": true,
        "rightAssociative": false,
        "isLoop": false,
        "isAssign": false,
        "prefix": true,
        "postfix": false,
        "binop": null,
        "updateContext": null
      },
      "value": "typeof",
      "start": 272,
      "end": 278,
      "loc": {
        "start": {
          "line": 15,
          "column": 8
        },
        "end": {
          "line": 15,
          "column": 14
        }
      }
    },
    {
      "type": {
        "label": "name",
        "beforeExpr": false,
        "startsExpr": true,
        "rightAssociative": false,
        "isLoop": false,
        "isAssign": false,
        "prefix": false,
        "postfix": false,
        "binop": null
      },
      "value": "Error",
      "start": 279,
      "end": 284,
      "loc": {
        "start": {
          "line": 15,
          "column": 15
        },
        "end": {
          "line": 15,
          "column": 20
        }
      }
    },
    {
      "type": {
        "label": ".",
        "beforeExpr": false,
        "startsExpr": false,
        "rightAssociative": false,
        "isLoop": false,
        "isAssign": false,
        "prefix": false,
        "postfix": false,
        "binop": null,
        "updateContext": null
      },
      "start": 284,
      "end": 285,
      "loc": {
        "start": {
          "line": 15,
          "column": 20
        },
        "end": {
          "line": 15,
          "column": 21
        }
      }
    },
    {
      "type": {
        "label": "name",
        "beforeExpr": false,
        "startsExpr": true,
        "rightAssociative": false,
        "isLoop": false,
        "isAssign": false,
        "prefix": false,
        "postfix": false,
        "binop": null
      },
      "value": "captureStackTrace",
      "start": 285,
      "end": 302,
      "loc": {
        "start": {
          "line": 15,
          "column": 21
        },
        "end": {
          "line": 15,
          "column": 38
        }
      }
    },
    {
      "type": {
        "label": "==/!=",
        "beforeExpr": true,
        "startsExpr": false,
        "rightAssociative": false,
        "isLoop": false,
        "isAssign": false,
        "prefix": false,
        "postfix": false,
        "binop": 6,
        "updateContext": null
      },
      "value": "===",
      "start": 303,
      "end": 306,
      "loc": {
        "start": {
          "line": 15,
          "column": 39
        },
        "end": {
          "line": 15,
          "column": 42
        }
      }
    },
    {
      "type": {
        "label": "string",
        "beforeExpr": false,
        "startsExpr": true,
        "rightAssociative": false,
        "isLoop": false,
        "isAssign": false,
        "prefix": false,
        "postfix": false,
        "binop": null,
        "updateContext": null
      },
      "value": "function",
      "start": 307,
      "end": 317,
      "loc": {
        "start": {
          "line": 15,
          "column": 43
        },
        "end": {
          "line": 15,
          "column": 53
        }
      }
    },
    {
      "type": {
        "label": ")",
        "beforeExpr": false,
        "startsExpr": false,
        "rightAssociative": false,
        "isLoop": false,
        "isAssign": false,
        "prefix": false,
        "postfix": false,
        "binop": null
      },
      "start": 317,
      "end": 318,
      "loc": {
        "start": {
          "line": 15,
          "column": 53
        },
        "end": {
          "line": 15,
          "column": 54
        }
      }
    },
    {
      "type": {
        "label": "{",
        "beforeExpr": true,
        "startsExpr": true,
        "rightAssociative": false,
        "isLoop": false,
        "isAssign": false,
        "prefix": false,
        "postfix": false,
        "binop": null
      },
      "start": 319,
      "end": 320,
      "loc": {
        "start": {
          "line": 15,
          "column": 55
        },
        "end": {
          "line": 15,
          "column": 56
        }
      }
    },
    {
      "type": {
        "label": "name",
        "beforeExpr": false,
        "startsExpr": true,
        "rightAssociative": false,
        "isLoop": false,
        "isAssign": false,
        "prefix": false,
        "postfix": false,
        "binop": null
      },
      "value": "Error",
      "start": 327,
      "end": 332,
      "loc": {
        "start": {
          "line": 16,
          "column": 6
        },
        "end": {
          "line": 16,
          "column": 11
        }
      }
    },
    {
      "type": {
        "label": ".",
        "beforeExpr": false,
        "startsExpr": false,
        "rightAssociative": false,
        "isLoop": false,
        "isAssign": false,
        "prefix": false,
        "postfix": false,
        "binop": null,
        "updateContext": null
      },
      "start": 332,
      "end": 333,
      "loc": {
        "start": {
          "line": 16,
          "column": 11
        },
        "end": {
          "line": 16,
          "column": 12
        }
      }
    },
    {
      "type": {
        "label": "name",
        "beforeExpr": false,
        "startsExpr": true,
        "rightAssociative": false,
        "isLoop": false,
        "isAssign": false,
        "prefix": false,
        "postfix": false,
        "binop": null
      },
      "value": "captureStackTrace",
      "start": 333,
      "end": 350,
      "loc": {
        "start": {
          "line": 16,
          "column": 12
        },
        "end": {
          "line": 16,
          "column": 29
        }
      }
    },
    {
      "type": {
        "label": "(",
        "beforeExpr": true,
        "startsExpr": true,
        "rightAssociative": false,
        "isLoop": false,
        "isAssign": false,
        "prefix": false,
        "postfix": false,
        "binop": null
      },
      "start": 350,
      "end": 351,
      "loc": {
        "start": {
          "line": 16,
          "column": 29
        },
        "end": {
          "line": 16,
          "column": 30
        }
      }
    },
    {
      "type": {
        "label": "this",
        "keyword": "this",
        "beforeExpr": false,
        "startsExpr": true,
        "rightAssociative": false,
        "isLoop": false,
        "isAssign": false,
        "prefix": false,
        "postfix": false,
        "binop": null,
        "updateContext": null
      },
      "value": "this",
      "start": 351,
      "end": 355,
      "loc": {
        "start": {
          "line": 16,
          "column": 30
        },
        "end": {
          "line": 16,
          "column": 34
        }
      }
    },
    {
      "type": {
        "label": ",",
        "beforeExpr": true,
        "startsExpr": false,
        "rightAssociative": false,
        "isLoop": false,
        "isAssign": false,
        "prefix": false,
        "postfix": false,
        "binop": null,
        "updateContext": null
      },
      "start": 355,
      "end": 356,
      "loc": {
        "start": {
          "line": 16,
          "column": 34
        },
        "end": {
          "line": 16,
          "column": 35
        }
      }
    },
    {
      "type": {
        "label": "this",
        "keyword": "this",
        "beforeExpr": false,
        "startsExpr": true,
        "rightAssociative": false,
        "isLoop": false,
        "isAssign": false,
        "prefix": false,
        "postfix": false,
        "binop": null,
        "updateContext": null
      },
      "value": "this",
      "start": 357,
      "end": 361,
      "loc": {
        "start": {
          "line": 16,
          "column": 36
        },
        "end": {
          "line": 16,
          "column": 40
        }
      }
    },
    {
      "type": {
        "label": ".",
        "beforeExpr": false,
        "startsExpr": false,
        "rightAssociative": false,
        "isLoop": false,
        "isAssign": false,
        "prefix": false,
        "postfix": false,
        "binop": null,
        "updateContext": null
      },
      "start": 361,
      "end": 362,
      "loc": {
        "start": {
          "line": 16,
          "column": 40
        },
        "end": {
          "line": 16,
          "column": 41
        }
      }
    },
    {
      "type": {
        "label": "name",
        "beforeExpr": false,
        "startsExpr": true,
        "rightAssociative": false,
        "isLoop": false,
        "isAssign": false,
        "prefix": false,
        "postfix": false,
        "binop": null
      },
      "value": "constructor",
      "start": 362,
      "end": 373,
      "loc": {
        "start": {
          "line": 16,
          "column": 41
        },
        "end": {
          "line": 16,
          "column": 52
        }
      }
    },
    {
      "type": {
        "label": ")",
        "beforeExpr": false,
        "startsExpr": false,
        "rightAssociative": false,
        "isLoop": false,
        "isAssign": false,
        "prefix": false,
        "postfix": false,
        "binop": null
      },
      "start": 373,
      "end": 374,
      "loc": {
        "start": {
          "line": 16,
          "column": 52
        },
        "end": {
          "line": 16,
          "column": 53
        }
      }
    },
    {
      "type": {
        "label": ";",
        "beforeExpr": true,
        "startsExpr": false,
        "rightAssociative": false,
        "isLoop": false,
        "isAssign": false,
        "prefix": false,
        "postfix": false,
        "binop": null,
        "updateContext": null
      },
      "start": 374,
      "end": 375,
      "loc": {
        "start": {
          "line": 16,
          "column": 53
        },
        "end": {
          "line": 16,
          "column": 54
        }
      }
    },
    {
      "type": {
        "label": "}",
        "beforeExpr": false,
        "startsExpr": false,
        "rightAssociative": false,
        "isLoop": false,
        "isAssign": false,
        "prefix": false,
        "postfix": false,
        "binop": null
      },
      "start": 380,
      "end": 381,
      "loc": {
        "start": {
          "line": 17,
          "column": 4
        },
        "end": {
          "line": 17,
          "column": 5
        }
      }
    },
    {
      "type": {
        "label": "else",
        "keyword": "else",
        "beforeExpr": true,
        "startsExpr": false,
        "rightAssociative": false,
        "isLoop": false,
        "isAssign": false,
        "prefix": false,
        "postfix": false,
        "binop": null,
        "updateContext": null
      },
      "value": "else",
      "start": 382,
      "end": 386,
      "loc": {
        "start": {
          "line": 17,
          "column": 6
        },
        "end": {
          "line": 17,
          "column": 10
        }
      }
    },
    {
      "type": {
        "label": "{",
        "beforeExpr": true,
        "startsExpr": true,
        "rightAssociative": false,
        "isLoop": false,
        "isAssign": false,
        "prefix": false,
        "postfix": false,
        "binop": null
      },
      "start": 387,
      "end": 388,
      "loc": {
        "start": {
          "line": 17,
          "column": 11
        },
        "end": {
          "line": 17,
          "column": 12
        }
      }
    },
    {
      "type": "CommentBlock",
      "value": "*\n       * @ignore\n       ",
      "start": 395,
      "end": 425,
      "loc": {
        "start": {
          "line": 18,
          "column": 6
        },
        "end": {
          "line": 20,
          "column": 9
        }
      }
    },
    {
      "type": {
        "label": "this",
        "keyword": "this",
        "beforeExpr": false,
        "startsExpr": true,
        "rightAssociative": false,
        "isLoop": false,
        "isAssign": false,
        "prefix": false,
        "postfix": false,
        "binop": null,
        "updateContext": null
      },
      "value": "this",
      "start": 432,
      "end": 436,
      "loc": {
        "start": {
          "line": 21,
          "column": 6
        },
        "end": {
          "line": 21,
          "column": 10
        }
      }
    },
    {
      "type": {
        "label": ".",
        "beforeExpr": false,
        "startsExpr": false,
        "rightAssociative": false,
        "isLoop": false,
        "isAssign": false,
        "prefix": false,
        "postfix": false,
        "binop": null,
        "updateContext": null
      },
      "start": 436,
      "end": 437,
      "loc": {
        "start": {
          "line": 21,
          "column": 10
        },
        "end": {
          "line": 21,
          "column": 11
        }
      }
    },
    {
      "type": {
        "label": "name",
        "beforeExpr": false,
        "startsExpr": true,
        "rightAssociative": false,
        "isLoop": false,
        "isAssign": false,
        "prefix": false,
        "postfix": false,
        "binop": null
      },
      "value": "stack",
      "start": 437,
      "end": 442,
      "loc": {
        "start": {
          "line": 21,
          "column": 11
        },
        "end": {
          "line": 21,
          "column": 16
        }
      }
    },
    {
      "type": {
        "label": "=",
        "beforeExpr": true,
        "startsExpr": false,
        "rightAssociative": false,
        "isLoop": false,
        "isAssign": true,
        "prefix": false,
        "postfix": false,
        "binop": null,
        "updateContext": null
      },
      "value": "=",
      "start": 443,
      "end": 444,
      "loc": {
        "start": {
          "line": 21,
          "column": 17
        },
        "end": {
          "line": 21,
          "column": 18
        }
      }
    },
    {
      "type": {
        "label": "(",
        "beforeExpr": true,
        "startsExpr": true,
        "rightAssociative": false,
        "isLoop": false,
        "isAssign": false,
        "prefix": false,
        "postfix": false,
        "binop": null
      },
      "start": 445,
      "end": 446,
      "loc": {
        "start": {
          "line": 21,
          "column": 19
        },
        "end": {
          "line": 21,
          "column": 20
        }
      }
    },
    {
      "type": {
        "label": "new",
        "keyword": "new",
        "beforeExpr": true,
        "startsExpr": true,
        "rightAssociative": false,
        "isLoop": false,
        "isAssign": false,
        "prefix": false,
        "postfix": false,
        "binop": null,
        "updateContext": null
      },
      "value": "new",
      "start": 446,
      "end": 449,
      "loc": {
        "start": {
          "line": 21,
          "column": 20
        },
        "end": {
          "line": 21,
          "column": 23
        }
      }
    },
    {
      "type": {
        "label": "name",
        "beforeExpr": false,
        "startsExpr": true,
        "rightAssociative": false,
        "isLoop": false,
        "isAssign": false,
        "prefix": false,
        "postfix": false,
        "binop": null
      },
      "value": "Error",
      "start": 450,
      "end": 455,
      "loc": {
        "start": {
          "line": 21,
          "column": 24
        },
        "end": {
          "line": 21,
          "column": 29
        }
      }
    },
    {
      "type": {
        "label": "(",
        "beforeExpr": true,
        "startsExpr": true,
        "rightAssociative": false,
        "isLoop": false,
        "isAssign": false,
        "prefix": false,
        "postfix": false,
        "binop": null
      },
      "start": 455,
      "end": 456,
      "loc": {
        "start": {
          "line": 21,
          "column": 29
        },
        "end": {
          "line": 21,
          "column": 30
        }
      }
    },
    {
      "type": {
        "label": "name",
        "beforeExpr": false,
        "startsExpr": true,
        "rightAssociative": false,
        "isLoop": false,
        "isAssign": false,
        "prefix": false,
        "postfix": false,
        "binop": null
      },
      "value": "message",
      "start": 456,
      "end": 463,
      "loc": {
        "start": {
          "line": 21,
          "column": 30
        },
        "end": {
          "line": 21,
          "column": 37
        }
      }
    },
    {
      "type": {
        "label": ")",
        "beforeExpr": false,
        "startsExpr": false,
        "rightAssociative": false,
        "isLoop": false,
        "isAssign": false,
        "prefix": false,
        "postfix": false,
        "binop": null
      },
      "start": 463,
      "end": 464,
      "loc": {
        "start": {
          "line": 21,
          "column": 37
        },
        "end": {
          "line": 21,
          "column": 38
        }
      }
    },
    {
      "type": {
        "label": ")",
        "beforeExpr": false,
        "startsExpr": false,
        "rightAssociative": false,
        "isLoop": false,
        "isAssign": false,
        "prefix": false,
        "postfix": false,
        "binop": null
      },
      "start": 464,
      "end": 465,
      "loc": {
        "start": {
          "line": 21,
          "column": 38
        },
        "end": {
          "line": 21,
          "column": 39
        }
      }
    },
    {
      "type": {
        "label": ".",
        "beforeExpr": false,
        "startsExpr": false,
        "rightAssociative": false,
        "isLoop": false,
        "isAssign": false,
        "prefix": false,
        "postfix": false,
        "binop": null,
        "updateContext": null
      },
      "start": 465,
      "end": 466,
      "loc": {
        "start": {
          "line": 21,
          "column": 39
        },
        "end": {
          "line": 21,
          "column": 40
        }
      }
    },
    {
      "type": {
        "label": "name",
        "beforeExpr": false,
        "startsExpr": true,
        "rightAssociative": false,
        "isLoop": false,
        "isAssign": false,
        "prefix": false,
        "postfix": false,
        "binop": null
      },
      "value": "stack",
      "start": 466,
      "end": 471,
      "loc": {
        "start": {
          "line": 21,
          "column": 40
        },
        "end": {
          "line": 21,
          "column": 45
        }
      }
    },
    {
      "type": {
        "label": ";",
        "beforeExpr": true,
        "startsExpr": false,
        "rightAssociative": false,
        "isLoop": false,
        "isAssign": false,
        "prefix": false,
        "postfix": false,
        "binop": null,
        "updateContext": null
      },
      "start": 471,
      "end": 472,
      "loc": {
        "start": {
          "line": 21,
          "column": 45
        },
        "end": {
          "line": 21,
          "column": 46
        }
      }
    },
    {
      "type": {
        "label": "}",
        "beforeExpr": false,
        "startsExpr": false,
        "rightAssociative": false,
        "isLoop": false,
        "isAssign": false,
        "prefix": false,
        "postfix": false,
        "binop": null
      },
      "start": 477,
      "end": 478,
      "loc": {
        "start": {
          "line": 22,
          "column": 4
        },
        "end": {
          "line": 22,
          "column": 5
        }
      }
    },
    {
      "type": {
        "label": "}",
        "beforeExpr": false,
        "startsExpr": false,
        "rightAssociative": false,
        "isLoop": false,
        "isAssign": false,
        "prefix": false,
        "postfix": false,
        "binop": null
      },
      "start": 481,
      "end": 482,
      "loc": {
        "start": {
          "line": 23,
          "column": 2
        },
        "end": {
          "line": 23,
          "column": 3
        }
      }
    },
    {
      "type": {
        "label": "}",
        "beforeExpr": false,
        "startsExpr": false,
        "rightAssociative": false,
        "isLoop": false,
        "isAssign": false,
        "prefix": false,
        "postfix": false,
        "binop": null
      },
      "start": 483,
      "end": 484,
      "loc": {
        "start": {
          "line": 24,
          "column": 0
        },
        "end": {
          "line": 24,
          "column": 1
        }
      }
    },
    {
      "type": {
        "label": "eof",
        "beforeExpr": false,
        "startsExpr": false,
        "rightAssociative": false,
        "isLoop": false,
        "isAssign": false,
        "prefix": false,
        "postfix": false,
        "binop": null,
        "updateContext": null
      },
      "start": 485,
      "end": 485,
      "loc": {
        "start": {
          "line": 25,
          "column": 0
        },
        "end": {
          "line": 25,
          "column": 0
        }
      }
    }
  ]
}